{"summaries":[{"symbol":{"__symbol":0,"members":[]},"metadata":{"__symbolic":"class","members":{"children":[{"__symbolic":"property","decorators":[{"__symbolic":"call","expression":{"__symbol":1,"members":[]},"arguments":[{"__symbol":2,"members":[]}]}]}],"wrapper":[{"__symbolic":"property","decorators":[{"__symbolic":"call","expression":{"__symbol":3,"members":[]},"arguments":["wrapper"]}]}],"container":[{"__symbolic":"property","decorators":[{"__symbolic":"call","expression":{"__symbol":3,"members":[]},"arguments":["container"]}]}],"arrows":[{"__symbolic":"property","decorators":[{"__symbolic":"call","expression":{"__symbol":4,"members":[]},"arguments":[{"__symbol":5,"members":[]}]}]}],"height":[{"__symbolic":"property","decorators":[{"__symbolic":"call","expression":{"__symbol":6,"members":[]},"arguments":["style.height.px"]}]}],"__ctor__":[{"__symbolic":"constructor","parameters":[{"__symbol":7,"members":[]},{"__symbol":8,"members":[]},{"__symbol":9,"members":[]}]}],"ngOnInit":[{"__symbolic":"method"}],"ngAfterContentInit":[{"__symbolic":"method"}],"ngAfterViewInit":[{"__symbolic":"method"}],"onMouseDown":[{"__symbolic":"method"}],"onMouseUp":[{"__symbolic":"method"}],"onMouseWheelFirefox":[{"__symbolic":"method"}],"onMouseWheel":[{"__symbolic":"method"}],"onTouchStart":[{"__symbolic":"method"}],"onTouchEnd":[{"__symbolic":"method"}],"onTouchMove":[{"__symbolic":"method"}],"scrollLeftAnimate":[{"__symbolic":"method"}]}},"type":{"summaryKind":1,"type":{"reference":{"__symbol":0,"members":[]},"diDeps":[{"isAttribute":false,"isHost":false,"isSelf":false,"isSkipSelf":false,"isOptional":false,"token":{"identifier":{"reference":{"__symbol":7,"members":[]}}}},{"isAttribute":false,"isHost":false,"isSelf":false,"isSkipSelf":false,"isOptional":false,"token":{"identifier":{"reference":{"__symbol":8,"members":[]}}}},{"isAttribute":false,"isHost":false,"isSelf":false,"isSkipSelf":false,"isOptional":false,"token":{"identifier":{"reference":{"__symbol":9,"members":[]}}}}],"lifecycleHooks":[0,4,6]},"isComponent":true,"selector":"scroll-slider","inputs":{},"outputs":{},"hostListeners":{},"hostProperties":{"style.height.px":"height"},"hostAttributes":{},"providers":[],"viewProviders":[],"queries":[{"selectors":[{"identifier":{"reference":{"__symbol":2,"members":[]}}}],"first":false,"descendants":false,"propertyName":"children","read":null}],"viewQueries":[{"selectors":[{"value":"wrapper"}],"first":true,"descendants":true,"propertyName":"wrapper","read":null},{"selectors":[{"value":"container"}],"first":true,"descendants":true,"propertyName":"container","read":null},{"selectors":[{"identifier":{"reference":{"__symbol":5,"members":[]}}}],"first":false,"descendants":true,"propertyName":"arrows","read":null}],"entryComponents":[],"changeDetection":0,"template":{"animations":[],"ngContentSelectors":["*"],"encapsulation":0},"componentViewType":{"__symbol":10,"members":[]},"rendererType":{"__symbol":11,"members":[]},"componentFactory":{"__symbol":12,"members":[]}}}],"symbols":[{"__symbol":0,"name":"SliderComponent","filePath":"/Users/darek/ProjectsMac/npm/ng2-scroll-slider/src/slider/slider.component.d.ts"},{"__symbol":1,"name":"ContentChildren","filePath":"/Users/darek/ProjectsMac/npm/ng2-scroll-slider/node_modules/@angular/core/core.d.ts"},{"__symbol":2,"name":"ChildDirective","filePath":"/Users/darek/ProjectsMac/npm/ng2-scroll-slider/src/slider/child.directive.d.ts"},{"__symbol":3,"name":"ViewChild","filePath":"/Users/darek/ProjectsMac/npm/ng2-scroll-slider/node_modules/@angular/core/core.d.ts"},{"__symbol":4,"name":"ViewChildren","filePath":"/Users/darek/ProjectsMac/npm/ng2-scroll-slider/node_modules/@angular/core/core.d.ts"},{"__symbol":5,"name":"ArrowDirective","filePath":"/Users/darek/ProjectsMac/npm/ng2-scroll-slider/src/slider/arrow.directive.d.ts"},{"__symbol":6,"name":"HostBinding","filePath":"/Users/darek/ProjectsMac/npm/ng2-scroll-slider/node_modules/@angular/core/core.d.ts"},{"__symbol":7,"name":"Renderer","filePath":"/Users/darek/ProjectsMac/npm/ng2-scroll-slider/node_modules/@angular/core/core.d.ts"},{"__symbol":8,"name":"ChangeDetectorRef","filePath":"/Users/darek/ProjectsMac/npm/ng2-scroll-slider/node_modules/@angular/core/core.d.ts"},{"__symbol":9,"name":"NgZone","filePath":"/Users/darek/ProjectsMac/npm/ng2-scroll-slider/node_modules/@angular/core/core.d.ts"},{"__symbol":10,"name":"View_SliderComponent_0","filePath":"/Users/darek/ProjectsMac/npm/ng2-scroll-slider/src/slider/slider.component.ngfactory.d.ts"},{"__symbol":11,"name":"RenderType_SliderComponent","filePath":"/Users/darek/ProjectsMac/npm/ng2-scroll-slider/src/slider/slider.component.ngfactory.d.ts"},{"__symbol":12,"name":"SliderComponentNgFactory","filePath":"/Users/darek/ProjectsMac/npm/ng2-scroll-slider/src/slider/slider.component.ngfactory.d.ts"}]}